crc_manager/__about__.py
crc_manager/__init__.py
crc_manager/main.py
crc_manager/update.py
crc_manager/util.py
crc_manager-0.1.1.dist-info/LICENSE
crc_manager-0.1.1.dist-info/METADATA
crc_manager-0.1.1.dist-info/WHEEL
crc_manager-0.1.1.dist-info/entry_points.txt
crc_manager-0.1.1.dist-info/top_level.txt
crc_manager-0.1.1.dist-info/RECORD
